comfyui_embedded_docs/__init__.py
comfyui_embedded_docs/docs/BasicScheduler/en.md
comfyui_embedded_docs/docs/BasicScheduler/es.md
comfyui_embedded_docs/docs/BasicScheduler/fr.md
comfyui_embedded_docs/docs/BasicScheduler/ja.md
comfyui_embedded_docs/docs/BasicScheduler/ko.md
comfyui_embedded_docs/docs/BasicScheduler/ru.md
comfyui_embedded_docs/docs/BasicScheduler/zh.md
comfyui_embedded_docs/docs/Canny/en.md
comfyui_embedded_docs/docs/Canny/es.md
comfyui_embedded_docs/docs/Canny/fr.md
comfyui_embedded_docs/docs/Canny/ja.md
comfyui_embedded_docs/docs/Canny/ko.md
comfyui_embedded_docs/docs/Canny/ru.md
comfyui_embedded_docs/docs/Canny/zh.md
comfyui_embedded_docs/docs/Canny/asset/compare.webp
comfyui_embedded_docs/docs/Canny/asset/input.webp
comfyui_embedded_docs/docs/CheckpointLoaderSimple/en.md
comfyui_embedded_docs/docs/CheckpointLoaderSimple/es.md
comfyui_embedded_docs/docs/CheckpointLoaderSimple/fr.md
comfyui_embedded_docs/docs/CheckpointLoaderSimple/ja.md
comfyui_embedded_docs/docs/CheckpointLoaderSimple/ko.md
comfyui_embedded_docs/docs/CheckpointLoaderSimple/ru.md
comfyui_embedded_docs/docs/CheckpointLoaderSimple/zh.md
comfyui_embedded_docs/docs/CheckpointSave/en.md
comfyui_embedded_docs/docs/CheckpointSave/es.md
comfyui_embedded_docs/docs/CheckpointSave/fr.md
comfyui_embedded_docs/docs/CheckpointSave/ja.md
comfyui_embedded_docs/docs/CheckpointSave/ko.md
comfyui_embedded_docs/docs/CheckpointSave/ru.md
comfyui_embedded_docs/docs/CheckpointSave/zh.md
comfyui_embedded_docs/docs/ClipLoader/en.md
comfyui_embedded_docs/docs/ClipLoader/es.md
comfyui_embedded_docs/docs/ClipLoader/fr.md
comfyui_embedded_docs/docs/ClipLoader/ja.md
comfyui_embedded_docs/docs/ClipLoader/ko.md
comfyui_embedded_docs/docs/ClipLoader/ru.md
comfyui_embedded_docs/docs/ClipLoader/zh.md
comfyui_embedded_docs/docs/ClipMergeSimple/en.md
comfyui_embedded_docs/docs/ClipMergeSimple/es.md
comfyui_embedded_docs/docs/ClipMergeSimple/fr.md
comfyui_embedded_docs/docs/ClipMergeSimple/ja.md
comfyui_embedded_docs-0.2.6.dist-info/licenses/LICENSE
comfyui_embedded_docs-0.2.6.dist-info/METADATA
comfyui_embedded_docs-0.2.6.dist-info/WHEEL
comfyui_embedded_docs-0.2.6.dist-info/top_level.txt
comfyui_embedded_docs-0.2.6.dist-info/RECORD
