Metadata-Version: 2.4
Name: comfyui-embedded-docs
Version: 0.2.6
Summary: Embedded documentation for ComfyUI nodes
Author: Comfy-Org
License-Expression: GPL-3.0
Project-URL: repository, https://github.com/Comfy-Org/embedded-docs
Classifier: Programming Language :: Python :: 3
Classifier: Operating System :: OS Independent
Requires-Python: >=3.9
License-File: LICENSE
Dynamic: license-file
